LICENSE
README.md
setup.py
awsdeepracer_control/__init__.py
awsdeepracer_control/awsdeepracer_control.py
awsdeepracer_control.egg-info/PKG-INFO
awsdeepracer_control.egg-info/SOURCES.txt
awsdeepracer_control.egg-info/dependency_links.txt
awsdeepracer_control.egg-info/requires.txt
awsdeepracer_control.egg-info/top_level.txt