Metadata-Version: 2.1
Name: awsdeepracer-control
Version: 0.2.0
Summary: awsdeepracer_control is a rewrite python package for control the DeepRacer vehicle via HTTP API.
Home-page: https://github.com/lshw54/awsdeepracer_control
Author: lshw54
Author-email: lshw.5454@gmail.com
License: MIT
Requires-Python: >=3.6
License-File: LICENSE
